{"nodes": [{"id": "docs_mail_transport_plan_agent_mail_phase_transitions", "label": "Agent Mail Phase Transitions", "file_type": "document", "source_file": "docs/mail-transport-plan.md", "source_location": "# Agent Mail-Driven Phase Transitions: Implementation Plan", "source_url": null, "captured_at": null, "author": null, "contributor": null}, {"id": "docs_mail_transport_plan_phase_prompt_externalization", "label": "Phase Prompt Externalization", "file_type": "concept", "source_file": "docs/mail-transport-plan.md", "source_location": "## Part 2: Externalized Prompts and Workflow Config", "source_url": null, "captured_at": null, "author": null, "contributor": null}, {"id": "docs_mail_transport_plan_inbox_feedback_read_path", "label": "Inbox Feedback Read Path", "file_type": "concept", "source_file": "docs/mail-transport-plan.md", "source_location": "## What's Missing", "source_url": null, "captured_at": null, "author": null, "contributor": null}], "edges": [{"source": "docs_mail_transport_plan_agent_mail_phase_transitions", "target": "docs_mail_transport_plan_inbox_feedback_read_path", "relation": "implements", "confidence": "EXTRACTED", "confidence_score": 1.0, "source_file": "docs/mail-transport-plan.md", "source_location": "## What's Missing", "weight": 1.0}, {"source": "docs_mail_transport_plan_agent_mail_phase_transitions", "target": "docs_mail_transport_plan_phase_prompt_externalization", "relation": "implements", "confidence": "EXTRACTED", "confidence_score": 1.0, "source_file": "docs/mail-transport-plan.md", "source_location": "## Part 2: Externalized Prompts and Workflow Config", "weight": 1.0}, {"source": "docs_mail_transport_plan_inbox_feedback_read_path", "target": "docs_cli_reference_agent_mail_commands", "relation": "conceptually_related_to", "confidence": "INFERRED", "confidence_score": 0.85, "source_file": "docs/mail-transport-plan.md", "source_location": "Inbox read path relies on the same Agent Mail concepts exposed through CLI inbox/mail commands.", "weight": 0.85}], "hyperedges": []}