{"nodes": [{"id": "users_ldangelo_foreman_worktrees_52ba0d80_913d_4880_871b_a81e308c34d4_foreman_51969_docs_prd_prd_kanban_task_board_md", "label": "PRD-kanban-task-board.md", "file_type": "document", "source_file": "docs/PRD/PRD-kanban-task-board.md", "source_location": "L1"}, {"id": "prd_prd_kanban_task_board_prd_kanban_task_board", "label": "PRD: Kanban Task Board", "file_type": "document", "source_file": "docs/PRD/PRD-kanban-task-board.md", "source_location": "L1"}, {"id": "prd_prd_kanban_task_board_1_product_summary", "label": "1. Product Summary", "file_type": "document", "source_file": "docs/PRD/PRD-kanban-task-board.md", "source_location": "L10"}, {"id": "prd_prd_kanban_task_board_problem_statement", "label": "Problem Statement", "file_type": "document", "source_file": "docs/PRD/PRD-kanban-task-board.md", "source_location": "L12"}, {"id": "prd_prd_kanban_task_board_solution_overview", "label": "Solution Overview", "file_type": "document", "source_file": "docs/PRD/PRD-kanban-task-board.md", "source_location": "L16"}, {"id": "prd_prd_kanban_task_board_value_proposition", "label": "Value Proposition", "file_type": "document", "source_file": "docs/PRD/PRD-kanban-task-board.md", "source_location": "L20"}, {"id": "prd_prd_kanban_task_board_2_user_analysis", "label": "2. User Analysis", "file_type": "document", "source_file": "docs/PRD/PRD-kanban-task-board.md", "source_location": "L29"}, {"id": "prd_prd_kanban_task_board_target_users", "label": "Target Users", "file_type": "document", "source_file": "docs/PRD/PRD-kanban-task-board.md", "source_location": "L31"}, {"id": "prd_prd_kanban_task_board_user_journey", "label": "User Journey", "file_type": "document", "source_file": "docs/PRD/PRD-kanban-task-board.md", "source_location": "L40"}, {"id": "prd_prd_kanban_task_board_3_goals_non_goals", "label": "3. Goals & Non-Goals", "file_type": "document", "source_file": "docs/PRD/PRD-kanban-task-board.md", "source_location": "L53"}, {"id": "prd_prd_kanban_task_board_goals", "label": "Goals", "file_type": "document", "source_file": "docs/PRD/PRD-kanban-task-board.md", "source_location": "L55"}, {"id": "prd_prd_kanban_task_board_non_goals", "label": "Non-Goals", "file_type": "document", "source_file": "docs/PRD/PRD-kanban-task-board.md", "source_location": "L66"}, {"id": "prd_prd_kanban_task_board_4_functional_requirements", "label": "4. Functional Requirements", "file_type": "document", "source_file": "docs/PRD/PRD-kanban-task-board.md", "source_location": "L78"}, {"id": "prd_prd_kanban_task_board_fr_1_board_rendering", "label": "FR-1: Board Rendering", "file_type": "document", "source_file": "docs/PRD/PRD-kanban-task-board.md", "source_location": "L80"}, {"id": "prd_prd_kanban_task_board_fr_2_navigation", "label": "FR-2: Navigation", "file_type": "document", "source_file": "docs/PRD/PRD-kanban-task-board.md", "source_location": "L91"}, {"id": "prd_prd_kanban_task_board_fr_3_status_change", "label": "FR-3: Status Change", "file_type": "document", "source_file": "docs/PRD/PRD-kanban-task-board.md", "source_location": "L106"}, {"id": "prd_prd_kanban_task_board_fr_4_close_task", "label": "FR-4: Close Task", "file_type": "document", "source_file": "docs/PRD/PRD-kanban-task-board.md", "source_location": "L118"}, {"id": "prd_prd_kanban_task_board_fr_5_edit_task_in_editor", "label": "FR-5: Edit Task in $EDITOR", "file_type": "document", "source_file": "docs/PRD/PRD-kanban-task-board.md", "source_location": "L127"}, {"id": "prd_prd_kanban_task_board_fr_6_task_detail_view", "label": "FR-6: Task Detail View", "file_type": "document", "source_file": "docs/PRD/PRD-kanban-task-board.md", "source_location": "L148"}, {"id": "prd_prd_kanban_task_board_fr_7_refresh", "label": "FR-7: Refresh", "file_type": "document", "source_file": "docs/PRD/PRD-kanban-task-board.md", "source_location": "L157"}, {"id": "prd_prd_kanban_task_board_fr_8_help_overlay", "label": "FR-8: Help Overlay", "file_type": "document", "source_file": "docs/PRD/PRD-kanban-task-board.md", "source_location": "L164"}, {"id": "prd_prd_kanban_task_board_5_non_functional_requirements", "label": "5. Non-Functional Requirements", "file_type": "document", "source_file": "docs/PRD/PRD-kanban-task-board.md", "source_location": "L175"}, {"id": "prd_prd_kanban_task_board_nfr_1_performance", "label": "NFR-1: Performance", "file_type": "document", "source_file": "docs/PRD/PRD-kanban-task-board.md", "source_location": "L177"}, {"id": "prd_prd_kanban_task_board_nfr_2_compatibility", "label": "NFR-2: Compatibility", "file_type": "document", "source_file": "docs/PRD/PRD-kanban-task-board.md", "source_location": "L182"}, {"id": "prd_prd_kanban_task_board_nfr_3_task_store_integration", "label": "NFR-3: Task Store Integration", "file_type": "document", "source_file": "docs/PRD/PRD-kanban-task-board.md", "source_location": "L188"}, {"id": "prd_prd_kanban_task_board_nfr_4_error_handling", "label": "NFR-4: Error Handling", "file_type": "document", "source_file": "docs/PRD/PRD-kanban-task-board.md", "source_location": "L193"}, {"id": "prd_prd_kanban_task_board_6_acceptance_criteria", "label": "6. Acceptance Criteria", "file_type": "document", "source_file": "docs/PRD/PRD-kanban-task-board.md", "source_location": "L201"}, {"id": "prd_prd_kanban_task_board_ac_1_board_renders_correctly", "label": "AC-1: Board Renders Correctly", "file_type": "document", "source_file": "docs/PRD/PRD-kanban-task-board.md", "source_location": "L203"}, {"id": "prd_prd_kanban_task_board_ac_2_navigation_works", "label": "AC-2: Navigation Works", "file_type": "document", "source_file": "docs/PRD/PRD-kanban-task-board.md", "source_location": "L209"}, {"id": "prd_prd_kanban_task_board_ac_3_status_change_works", "label": "AC-3: Status Change Works", "file_type": "document", "source_file": "docs/PRD/PRD-kanban-task-board.md", "source_location": "L215"}, {"id": "prd_prd_kanban_task_board_ac_4_close_works", "label": "AC-4: Close Works", "file_type": "document", "source_file": "docs/PRD/PRD-kanban-task-board.md", "source_location": "L221"}, {"id": "prd_prd_kanban_task_board_ac_5_editor_works", "label": "AC-5: Editor Works", "file_type": "document", "source_file": "docs/PRD/PRD-kanban-task-board.md", "source_location": "L226"}, {"id": "prd_prd_kanban_task_board_ac_6_task_detail_works", "label": "AC-6: Task Detail Works", "file_type": "document", "source_file": "docs/PRD/PRD-kanban-task-board.md", "source_location": "L232"}, {"id": "prd_prd_kanban_task_board_ac_7_help_works", "label": "AC-7: Help Works", "file_type": "document", "source_file": "docs/PRD/PRD-kanban-task-board.md", "source_location": "L236"}, {"id": "prd_prd_kanban_task_board_ac_8_error_handling", "label": "AC-8: Error Handling", "file_type": "document", "source_file": "docs/PRD/PRD-kanban-task-board.md", "source_location": "L240"}, {"id": "prd_prd_kanban_task_board_ac_9_performance", "label": "AC-9: Performance", "file_type": "document", "source_file": "docs/PRD/PRD-kanban-task-board.md", "source_location": "L244"}, {"id": "prd_prd_kanban_task_board_7_implementation_notes", "label": "7. Implementation Notes", "file_type": "document", "source_file": "docs/PRD/PRD-kanban-task-board.md", "source_location": "L250"}, {"id": "prd_prd_kanban_task_board_technology", "label": "Technology", "file_type": "document", "source_file": "docs/PRD/PRD-kanban-task-board.md", "source_location": "L252"}, {"id": "prd_prd_kanban_task_board_cli_surface", "label": "CLI Surface", "file_type": "document", "source_file": "docs/PRD/PRD-kanban-task-board.md", "source_location": "L258"}, {"id": "prd_prd_kanban_task_board_file_structure", "label": "File Structure", "file_type": "document", "source_file": "docs/PRD/PRD-kanban-task-board.md", "source_location": "L266"}, {"id": "prd_prd_kanban_task_board_dependency_none_uses_existing_foreman_task_cli", "label": "Dependency: None (uses existing foreman task CLI)", "file_type": "document", "source_file": "docs/PRD/PRD-kanban-task-board.md", "source_location": "L284"}], "edges": [{"source": "users_ldangelo_foreman_worktrees_52ba0d80_913d_4880_871b_a81e308c34d4_foreman_51969_docs_prd_prd_kanban_task_board_md", "target": "prd_prd_kanban_task_board_prd_kanban_task_board", "relation": "contains", "confidence": "EXTRACTED", "source_file": "docs/PRD/PRD-kanban-task-board.md", "source_location": "L1", "weight": 1.0}, {"source": "prd_prd_kanban_task_board_prd_kanban_task_board", "target": "prd_prd_kanban_task_board_1_product_summary", "relation": "contains", "confidence": "EXTRACTED", "source_file": "docs/PRD/PRD-kanban-task-board.md", "source_location": "L10", "weight": 1.0}, {"source": "prd_prd_kanban_task_board_1_product_summary", "target": "prd_prd_kanban_task_board_problem_statement", "relation": "contains", "confidence": "EXTRACTED", "source_file": "docs/PRD/PRD-kanban-task-board.md", "source_location": "L12", "weight": 1.0}, {"source": "prd_prd_kanban_task_board_1_product_summary", "target": "prd_prd_kanban_task_board_solution_overview", "relation": "contains", "confidence": "EXTRACTED", "source_file": "docs/PRD/PRD-kanban-task-board.md", "source_location": "L16", "weight": 1.0}, {"source": "prd_prd_kanban_task_board_1_product_summary", "target": "prd_prd_kanban_task_board_value_proposition", "relation": "contains", "confidence": "EXTRACTED", "source_file": "docs/PRD/PRD-kanban-task-board.md", "source_location": "L20", "weight": 1.0}, {"source": "prd_prd_kanban_task_board_prd_kanban_task_board", "target": "prd_prd_kanban_task_board_2_user_analysis", "relation": "contains", "confidence": "EXTRACTED", "source_file": "docs/PRD/PRD-kanban-task-board.md", "source_location": "L29", "weight": 1.0}, {"source": "prd_prd_kanban_task_board_2_user_analysis", "target": "prd_prd_kanban_task_board_target_users", "relation": "contains", "confidence": "EXTRACTED", "source_file": "docs/PRD/PRD-kanban-task-board.md", "source_location": "L31", "weight": 1.0}, {"source": "prd_prd_kanban_task_board_2_user_analysis", "target": "prd_prd_kanban_task_board_user_journey", "relation": "contains", "confidence": "EXTRACTED", "source_file": "docs/PRD/PRD-kanban-task-board.md", "source_location": "L40", "weight": 1.0}, {"source": "prd_prd_kanban_task_board_prd_kanban_task_board", "target": "prd_prd_kanban_task_board_3_goals_non_goals", "relation": "contains", "confidence": "EXTRACTED", "source_file": "docs/PRD/PRD-kanban-task-board.md", "source_location": "L53", "weight": 1.0}, {"source": "prd_prd_kanban_task_board_3_goals_non_goals", "target": "prd_prd_kanban_task_board_goals", "relation": "contains", "confidence": "EXTRACTED", "source_file": "docs/PRD/PRD-kanban-task-board.md", "source_location": "L55", "weight": 1.0}, {"source": "prd_prd_kanban_task_board_3_goals_non_goals", "target": "prd_prd_kanban_task_board_non_goals", "relation": "contains", "confidence": "EXTRACTED", "source_file": "docs/PRD/PRD-kanban-task-board.md", "source_location": "L66", "weight": 1.0}, {"source": "prd_prd_kanban_task_board_prd_kanban_task_board", "target": "prd_prd_kanban_task_board_4_functional_requirements", "relation": "contains", "confidence": "EXTRACTED", "source_file": "docs/PRD/PRD-kanban-task-board.md", "source_location": "L78", "weight": 1.0}, {"source": "prd_prd_kanban_task_board_4_functional_requirements", "target": "prd_prd_kanban_task_board_fr_1_board_rendering", "relation": "contains", "confidence": "EXTRACTED", "source_file": "docs/PRD/PRD-kanban-task-board.md", "source_location": "L80", "weight": 1.0}, {"source": "prd_prd_kanban_task_board_4_functional_requirements", "target": "prd_prd_kanban_task_board_fr_2_navigation", "relation": "contains", "confidence": "EXTRACTED", "source_file": "docs/PRD/PRD-kanban-task-board.md", "source_location": "L91", "weight": 1.0}, {"source": "prd_prd_kanban_task_board_4_functional_requirements", "target": "prd_prd_kanban_task_board_fr_3_status_change", "relation": "contains", "confidence": "EXTRACTED", "source_file": "docs/PRD/PRD-kanban-task-board.md", "source_location": "L106", "weight": 1.0}, {"source": "prd_prd_kanban_task_board_4_functional_requirements", "target": "prd_prd_kanban_task_board_fr_4_close_task", "relation": "contains", "confidence": "EXTRACTED", "source_file": "docs/PRD/PRD-kanban-task-board.md", "source_location": "L118", "weight": 1.0}, {"source": "prd_prd_kanban_task_board_4_functional_requirements", "target": "prd_prd_kanban_task_board_fr_5_edit_task_in_editor", "relation": "contains", "confidence": "EXTRACTED", "source_file": "docs/PRD/PRD-kanban-task-board.md", "source_location": "L127", "weight": 1.0}, {"source": "prd_prd_kanban_task_board_4_functional_requirements", "target": "prd_prd_kanban_task_board_fr_6_task_detail_view", "relation": "contains", "confidence": "EXTRACTED", "source_file": "docs/PRD/PRD-kanban-task-board.md", "source_location": "L148", "weight": 1.0}, {"source": "prd_prd_kanban_task_board_4_functional_requirements", "target": "prd_prd_kanban_task_board_fr_7_refresh", "relation": "contains", "confidence": "EXTRACTED", "source_file": "docs/PRD/PRD-kanban-task-board.md", "source_location": "L157", "weight": 1.0}, {"source": "prd_prd_kanban_task_board_4_functional_requirements", "target": "prd_prd_kanban_task_board_fr_8_help_overlay", "relation": "contains", "confidence": "EXTRACTED", "source_file": "docs/PRD/PRD-kanban-task-board.md", "source_location": "L164", "weight": 1.0}, {"source": "prd_prd_kanban_task_board_prd_kanban_task_board", "target": "prd_prd_kanban_task_board_5_non_functional_requirements", "relation": "contains", "confidence": "EXTRACTED", "source_file": "docs/PRD/PRD-kanban-task-board.md", "source_location": "L175", "weight": 1.0}, {"source": "prd_prd_kanban_task_board_5_non_functional_requirements", "target": "prd_prd_kanban_task_board_nfr_1_performance", "relation": "contains", "confidence": "EXTRACTED", "source_file": "docs/PRD/PRD-kanban-task-board.md", "source_location": "L177", "weight": 1.0}, {"source": "prd_prd_kanban_task_board_5_non_functional_requirements", "target": "prd_prd_kanban_task_board_nfr_2_compatibility", "relation": "contains", "confidence": "EXTRACTED", "source_file": "docs/PRD/PRD-kanban-task-board.md", "source_location": "L182", "weight": 1.0}, {"source": "prd_prd_kanban_task_board_5_non_functional_requirements", "target": "prd_prd_kanban_task_board_nfr_3_task_store_integration", "relation": "contains", "confidence": "EXTRACTED", "source_file": "docs/PRD/PRD-kanban-task-board.md", "source_location": "L188", "weight": 1.0}, {"source": "prd_prd_kanban_task_board_5_non_functional_requirements", "target": "prd_prd_kanban_task_board_nfr_4_error_handling", "relation": "contains", "confidence": "EXTRACTED", "source_file": "docs/PRD/PRD-kanban-task-board.md", "source_location": "L193", "weight": 1.0}, {"source": "prd_prd_kanban_task_board_prd_kanban_task_board", "target": "prd_prd_kanban_task_board_6_acceptance_criteria", "relation": "contains", "confidence": "EXTRACTED", "source_file": "docs/PRD/PRD-kanban-task-board.md", "source_location": "L201", "weight": 1.0}, {"source": "prd_prd_kanban_task_board_6_acceptance_criteria", "target": "prd_prd_kanban_task_board_ac_1_board_renders_correctly", "relation": "contains", "confidence": "EXTRACTED", "source_file": "docs/PRD/PRD-kanban-task-board.md", "source_location": "L203", "weight": 1.0}, {"source": "prd_prd_kanban_task_board_6_acceptance_criteria", "target": "prd_prd_kanban_task_board_ac_2_navigation_works", "relation": "contains", "confidence": "EXTRACTED", "source_file": "docs/PRD/PRD-kanban-task-board.md", "source_location": "L209", "weight": 1.0}, {"source": "prd_prd_kanban_task_board_6_acceptance_criteria", "target": "prd_prd_kanban_task_board_ac_3_status_change_works", "relation": "contains", "confidence": "EXTRACTED", "source_file": "docs/PRD/PRD-kanban-task-board.md", "source_location": "L215", "weight": 1.0}, {"source": "prd_prd_kanban_task_board_6_acceptance_criteria", "target": "prd_prd_kanban_task_board_ac_4_close_works", "relation": "contains", "confidence": "EXTRACTED", "source_file": "docs/PRD/PRD-kanban-task-board.md", "source_location": "L221", "weight": 1.0}, {"source": "prd_prd_kanban_task_board_6_acceptance_criteria", "target": "prd_prd_kanban_task_board_ac_5_editor_works", "relation": "contains", "confidence": "EXTRACTED", "source_file": "docs/PRD/PRD-kanban-task-board.md", "source_location": "L226", "weight": 1.0}, {"source": "prd_prd_kanban_task_board_6_acceptance_criteria", "target": "prd_prd_kanban_task_board_ac_6_task_detail_works", "relation": "contains", "confidence": "EXTRACTED", "source_file": "docs/PRD/PRD-kanban-task-board.md", "source_location": "L232", "weight": 1.0}, {"source": "prd_prd_kanban_task_board_6_acceptance_criteria", "target": "prd_prd_kanban_task_board_ac_7_help_works", "relation": "contains", "confidence": "EXTRACTED", "source_file": "docs/PRD/PRD-kanban-task-board.md", "source_location": "L236", "weight": 1.0}, {"source": "prd_prd_kanban_task_board_6_acceptance_criteria", "target": "prd_prd_kanban_task_board_ac_8_error_handling", "relation": "contains", "confidence": "EXTRACTED", "source_file": "docs/PRD/PRD-kanban-task-board.md", "source_location": "L240", "weight": 1.0}, {"source": "prd_prd_kanban_task_board_6_acceptance_criteria", "target": "prd_prd_kanban_task_board_ac_9_performance", "relation": "contains", "confidence": "EXTRACTED", "source_file": "docs/PRD/PRD-kanban-task-board.md", "source_location": "L244", "weight": 1.0}, {"source": "prd_prd_kanban_task_board_prd_kanban_task_board", "target": "prd_prd_kanban_task_board_7_implementation_notes", "relation": "contains", "confidence": "EXTRACTED", "source_file": "docs/PRD/PRD-kanban-task-board.md", "source_location": "L250", "weight": 1.0}, {"source": "prd_prd_kanban_task_board_7_implementation_notes", "target": "prd_prd_kanban_task_board_technology", "relation": "contains", "confidence": "EXTRACTED", "source_file": "docs/PRD/PRD-kanban-task-board.md", "source_location": "L252", "weight": 1.0}, {"source": "prd_prd_kanban_task_board_7_implementation_notes", "target": "prd_prd_kanban_task_board_cli_surface", "relation": "contains", "confidence": "EXTRACTED", "source_file": "docs/PRD/PRD-kanban-task-board.md", "source_location": "L258", "weight": 1.0}, {"source": "prd_prd_kanban_task_board_7_implementation_notes", "target": "prd_prd_kanban_task_board_file_structure", "relation": "contains", "confidence": "EXTRACTED", "source_file": "docs/PRD/PRD-kanban-task-board.md", "source_location": "L266", "weight": 1.0}, {"source": "prd_prd_kanban_task_board_7_implementation_notes", "target": "prd_prd_kanban_task_board_dependency_none_uses_existing_foreman_task_cli", "relation": "contains", "confidence": "EXTRACTED", "source_file": "docs/PRD/PRD-kanban-task-board.md", "source_location": "L284", "weight": 1.0}], "input_tokens": 0, "output_tokens": 0}